odoo/addons/storage_thumbnail/README.rst
odoo/addons/storage_thumbnail/__init__.py
odoo/addons/storage_thumbnail/__manifest__.py
odoo/addons/storage_thumbnail/data/ir_parameter.xml
odoo/addons/storage_thumbnail/i18n/it.po
odoo/addons/storage_thumbnail/i18n/storage_thumbnail.pot
odoo/addons/storage_thumbnail/models/__init__.py
odoo/addons/storage_thumbnail/models/storage_file.py
odoo/addons/storage_thumbnail/models/storage_thumbnail.py
odoo/addons/storage_thumbnail/models/thumbnail_mixin.py
odoo/addons/storage_thumbnail/readme/CONTRIBUTORS.md
odoo/addons/storage_thumbnail/readme/CREDITS.md
odoo/addons/storage_thumbnail/readme/DESCRIPTION.md
odoo/addons/storage_thumbnail/security/ir.model.access.csv
odoo/addons/storage_thumbnail/static/description/icon.png
odoo/addons/storage_thumbnail/static/description/index.html
odoo/addons/storage_thumbnail/tests/__init__.py
odoo/addons/storage_thumbnail/tests/models.py
odoo/addons/storage_thumbnail/tests/test_thumbnail.py
odoo/addons/storage_thumbnail/tests/static/akretion-logo.png
odoo/addons/storage_thumbnail/views/storage_thumbnail_view.xml
odoo_addon_storage_thumbnail-18.0.1.0.0.5.dist-info/METADATA
odoo_addon_storage_thumbnail-18.0.1.0.0.5.dist-info/WHEEL
odoo_addon_storage_thumbnail-18.0.1.0.0.5.dist-info/top_level.txt
odoo_addon_storage_thumbnail-18.0.1.0.0.5.dist-info/RECORD
