Metadata-Version: 2.1
Name: odoo-addon-storage_thumbnail
Version: 18.0.1.0.0.5
Requires-Python: >=3.10
Requires-Dist: odoo-addon-storage_file==18.0.*
Requires-Dist: odoo==18.0.*
Summary: Abstract module that add the possibility to have thumbnail
Home-page: https://github.com/OCA/storage
License: LGPL-3
Author: Akretion, Odoo Community Association (OCA)
Author-email: support@odoo-community.org
Classifier: Programming Language :: Python
Classifier: Framework :: Odoo
Classifier: Framework :: Odoo :: 18.0
Classifier: License :: OSI Approved :: GNU Lesser General Public License v3 (LGPLv3)
Classifier: Development Status :: 5 - Production/Stable
